django_placeholdit
