Metadata-Version: 1.1
Name: django-placeholdit
Version: 1.0.2
Summary: A fully featured drop-in replacement of placehold.it for Django
Home-page: https://github.com/stevelacey/django-placeholdit
Author: Steve Lacey
Author-email: steve@stevelacey.net
License: Copyright (c) 2015 Steve Lacey <steve@stevelacey.net>
